xsTool.py
xstool-0.0.1.dist-info/METADATA
xstool-0.0.1.dist-info/WHEEL
xstool-0.0.1.dist-info/RECORD
