Metadata-Version: 2.1
Name: xstool
Version: 0.0.1
Summary: simple module calculator
Author: xsvebmx
Author-email: m1rza.ismailov@yandex.ru
Requires-Python: >=3.8,<4.0
Classifier: Programming Language :: Python :: 3
Classifier: Programming Language :: Python :: 3.8
Classifier: Programming Language :: Python :: 3.9
Classifier: Programming Language :: Python :: 3.10
Classifier: Programming Language :: Python :: 3.11
